wfvkit/__init__.py
wfvkit/evaluate.py
wfvkit/leakage.py
wfvkit/metrics.py
wfvkit/splits.py
wfvkit-0.1.7.dist-info/licenses/LICENSE
wfvkit-0.1.7.dist-info/METADATA
wfvkit-0.1.7.dist-info/WHEEL
wfvkit-0.1.7.dist-info/top_level.txt
wfvkit-0.1.7.dist-info/RECORD
