Metadata-Version: 2.4
Name: wfvkit
Version: 0.1.7
Summary: Walk-forward validation utilities for time-series ML: splits, purge/embargo, and evaluation helpers.
Author: Mohsen Moghaddam
License-Expression: MIT
Project-URL: Homepage, https://github.com/Mohsentinal/wfv-toolkit
Project-URL: Repository, https://github.com/Mohsentinal/wfv-toolkit
Project-URL: Issues, https://github.com/Mohsentinal/wfv-toolkit/issues
Keywords: walk-forward,time-series,ml,cross-validation,purged,embargo,finance
Classifier: Programming Language :: Python :: 3
Classifier: Operating System :: OS Independent
Requires-Python: >=3.10
License-File: LICENSE
Provides-Extra: dev
Requires-Dist: pytest>=8.0; extra == "dev"
Requires-Dist: ruff>=0.6; extra == "dev"
Requires-Dist: build>=1.3; extra == "dev"
Dynamic: license-file
